thefuckllm/__init__.py
thefuckllm/cli.py
thefuckllm/client.py
thefuckllm/config.py
thefuckllm/engine.py
thefuckllm/logs.log
thefuckllm/models.py
thefuckllm/prompts.py
thefuckllm/retriever.py
thefuckllm/server.py
thefuckllm/typo_fixer.py
thefuckllm/providers/__init__.py
thefuckllm/providers/base.py
thefuckllm/providers/factory.py
thefuckllm/providers/litellm_provider.py
thefuckllm/providers/local.py
thefuckllm/shells/__init__.py
thefuckllm/shells/base.py
thefuckllm/shells/bash.py
thefuckllm/shells/fish.py
thefuckllm/shells/zsh.py
thefuckllm-0.2.0.dist-info/METADATA
thefuckllm-0.2.0.dist-info/WHEEL
thefuckllm-0.2.0.dist-info/entry_points.txt
thefuckllm-0.2.0.dist-info/RECORD
