Metadata-Version: 2.4
Name: thefuckllm
Version: 0.2.0
Summary: CLI helper powered by LLMs - fix commands and ask CLI questions
Project-URL: Homepage, https://github.com/alperiox/thefuckllm
Project-URL: Repository, https://github.com/alperiox/thefuckllm
Author: alperiox
License: MIT
Keywords: assistant,cli,llm,shell,terminal,thefuck
Classifier: Development Status :: 4 - Beta
Classifier: Environment :: Console
Classifier: Intended Audience :: Developers
Classifier: License :: OSI Approved :: MIT License
Classifier: Programming Language :: Python :: 3.12
Classifier: Topic :: Utilities
Requires-Python: >=3.12
Requires-Dist: fastembed>=0.7.4
Requires-Dist: huggingface-hub>=1.2.3
Requires-Dist: litellm>=1.55.0
Requires-Dist: llama-cpp-python>=0.3.16
Requires-Dist: numpy>=2.3.5
Requires-Dist: platformdirs>=4.5.1
Requires-Dist: tomli-w>=1.0.0
Requires-Dist: typer[all]>=0.20.0
